flask_middleware.py
setup.py
Flask_Middleware.egg-info/PKG-INFO
Flask_Middleware.egg-info/SOURCES.txt
Flask_Middleware.egg-info/dependency_links.txt
Flask_Middleware.egg-info/not-zip-safe
Flask_Middleware.egg-info/requires.txt
Flask_Middleware.egg-info/top_level.txt