Metadata-Version: 1.0
Name: Flask-Middleware
Version: 1.0
Summary: Basic middleware
Home-page: https://github.com/FranciscoCarbonell/flask-middleware
Author: Francisco Carbonell
Author-email: francabezo@gmail.com
License: MIT
Platform: any
